README.md
setup.cfg
setup.py
TextToOwO/__init__.py
TextToOwO/owo.py
TextToOwO.egg-info/PKG-INFO
TextToOwO.egg-info/SOURCES.txt
TextToOwO.egg-info/dependency_links.txt
TextToOwO.egg-info/top_level.txt