Metadata-Version: 1.1
Name: TextToOwO
Version: 2.0.1
Summary: OwO
Home-page: https://github.com/Zenrac/OwO-Translator/
Author: Zenrac
Author-email: zenrac@outlook.fr
License: UNKNOWN
Download-URL: https://github.com/Zenrac/TextToOwO/archive/v2.0.1.tar.gz
Keywords: OwO,Convewtew
Platform: UNKNOWN
